{
   "name" : "mulle-stacktrace",
   "version" : "0.2.9",
   "description" : "👣 Stracktrace support for various OS",
   "keywords" : [],
   "license" : "BSD-3-Clause",
   "repo" : "mulle-core/mulle-stacktrace",
   "src" : [
      "src/generic/include-private.h",
      "src/generic/include.h",
      "src/mulle-stacktrace-execinfo.c",
      "src/mulle-stacktrace-nop.c",
      "src/mulle-stacktrace-standalone.c",
      "src/mulle-stacktrace.c",
      "src/mulle-stacktrace.h",
      "src/reflect/_mulle-stacktrace-include-private.h",
      "src/reflect/_mulle-stacktrace-include.h",
      "src/reflect/_mulle-stacktrace-versioncheck.h"
   ],
   "dependencies" : {
      "mulle-core/mulle-dlfcn": "*"
   }
}
